VNH5019Controller/Commands.py
VNH5019Controller/Controller.py
VNH5019Controller/__init__.py
VNH5019_Serial_Controller-0.0.2.dist-info/LICENSE
VNH5019_Serial_Controller-0.0.2.dist-info/METADATA
VNH5019_Serial_Controller-0.0.2.dist-info/WHEEL
VNH5019_Serial_Controller-0.0.2.dist-info/top_level.txt
VNH5019_Serial_Controller-0.0.2.dist-info/RECORD
