Metadata-Version: 2.1
Name: VNH5019-Serial-Controller
Version: 0.0.2
Summary: A library for controlling a Pololu VNH5019 Motor Controller Shield via USB Serial and I2C.
Home-page: https://github.com/JoshuaBillson/VNH5019Controller
Author: Joshua Billson
Author-email: jmbillson@outlook.com
License: UNKNOWN
Platform: UNKNOWN
Classifier: Programming Language :: Python :: 3
Classifier: License :: OSI Approved :: MIT License
Classifier: Operating System :: OS Independent
Requires-Python: >=3.5
Requires-Dist: pyserial (==3.4)
Requires-Dist: smbus2 (==0.3.0)
